check_db/__init__.py
check_db/admin.py
check_db/apps.py
check_db/models.py
check_db/tests.py
check_db/views.py
check_db/management/__init__.py
check_db/management/commands/__init__.py
check_db/management/commands/checkdb.py
check_db/migrations/__init__.py
django_checkdb-1.2.dist-info/LICENSE
django_checkdb-1.2.dist-info/METADATA
django_checkdb-1.2.dist-info/WHEEL
django_checkdb-1.2.dist-info/top_level.txt
django_checkdb-1.2.dist-info/RECORD
