Metadata-Version: 2.1
Name: django-checkdb
Version: 1.2
Summary: That plugin checks a database connection
Author-email: pavelbeard <heavycream9090@icloud.com>
Project-URL: Homepage, https://github.com/pavelbeard/django-checkdb
Project-URL: Issues, https://github.com/pavelbeard/django-checkdb/issues
Classifier: Programming Language :: Python :: 3
Classifier: License :: OSI Approved :: MIT License
Classifier: Operating System :: OS Independent
Requires-Python: >=3.8
License-File: LICENSE
